{
    "title": {
        "locales": {
            "en": {
                "title_short": "Welcome!",
                "title_short_nav": "About me",
                "title_long_prefix": "Hello...",
                "title_long": "I'm {{Leo Hsu!}}"
            },
            "es": {
                "title_short": "¡Saludos!",
                "title_short_nav": "Sobre mí",
                "title_long_prefix": "Hola...",
                "title_long": "Soy {{Leo Hsu!}}"
            },
            "fr": {
                "title_short": "Salut !",
                "title_short_nav": "À propos",
                "title_long_prefix": "Salut...",
                "title_long": "Je suis {{Leo Hsu !}}"
            },
            "ko": {
                "title_short": "환영합니다!",
                "title_short_nav": "소개",
                "title_long_prefix": "안녕하세요...",
                "title_long": "저는 {{최민석}}입니다!"
            }
        }
    },

    "articles": [
        {
            "id": 1,
            "component": "ArticleInlineList",
            "locales": {},
            "settings": {
                "order_items_by": "id",
                "order_items_sort": "asc",
                "display_as_list_if_width_is_lower_than": 380
            },
            "items": [
                {
                    "id": 1,
                    "label": "Cupertino – CA",
                    "link": {"href": "", "tooltipString": ""},
                    "faIcon": "pi pi-map-Leoer"
                },
                {
                    "id": 2,
                    "label": "zoro061181249@gmail.com",
                    "link": {"href": "mailto:zoro061181249@gmail.com", "tooltipString": "email_me"},
                    "faIcon": "fa-regular fa-envelope"
                },
                {
                    "id": 3,
                    "label": "@zoro0611",
                    "link": {"href": "https://github.com/zoro0611", "tooltipString": "see_on_github"},
                    "faIcon": "fa-brands fa-github"
                }
            ]
        },

        {
            "id": 2,
            "component": "ArticleText",
            "locales": {
                "en": {"title": "{{A little bit}} about me..."},
                "es": {"title": "{{Un poco}} sobre mí..."},
                "fr": {"title": "{{Un peu}} à propos de moi..."},
                "ko": {"title": "저에 {{대해 조금}}..."}
            },
            "settings": {
                "order_items_by": "id",
                "order_items_sort": "asc"
            },
            "items": [
                {
                    "id": 1,
                    "img": "images/pictures/about-texts-image-1.png",
                    "faIcon": "",
                    "faIconColors": {"bg": "", "fill": ""},
                    "locales": {
                        "en": {
                            "text": "<p>I’m a {{PHP}} developer with [[over a decade]] of experience, specializing in backend development with some frontend work as well. I also have hands-on experience with C++, C#, Go, and Python in production environments.</p><p>This diverse background gives me the flexibility to adapt to a wide range of project needs, whether it's building scalable APIs, optimizing system performance, or contributing to full-stack solutions.</p><p>I look forward to collaborating [[with you!]]</p>"
                        },
                        "es": {
                            "text": "<p>Soy un desarrollador de {{PHP}} con [[más de una década]] de experiencia, especializado en desarrollo backend y con algo de experiencia en frontend. También tengo experiencia práctica en entornos de producción con C++, C#, Go y Python.</p><p>Este variado historial me permite adaptarme a una amplia gama de necesidades de proyectos, ya sea construyendo APIs escalables, optimizando el rendimiento de sistemas o contribuyendo a soluciones full-stack.</p><p>¡Espero con interés colaborar [[contigo!]]</p>"
                        },
                        "fr": {
                            "text": "<p>Je suis développeur {{PHP}} avec [[plus d'une décennie]] d'expérience, spécialisé dans le développement backend avec un peu de travail en frontend également. J'ai aussi de l'expérience en production avec les technologies C++, C#, Go et Python.</p><p>Ce parcours diversifié me permet de m'adapter à une large gamme de besoins de projets, qu'il s'agisse de créer des API évolutives, d'améliorer les performances système ou de participer à des solutions full-stack.</p><p>Je suis impatient de collaborer [[avec vous !]]</p>"
                        },
                        "ko": {
                            "text": "<p>저는 {{백엔드}} 개발을 전문으로 하고, 프론트엔드 작업도 일부 수행해온 [[10년 이상의]] 경력을 가진 PHP 개발자입니다. 또한 C++, C#, Go, Python 스택을 사용한 프로덕션 경험도 있습니다.</p><p>이 다양한 배경 덕분에 프로젝트의 다양한 요구에 유연하게 대처할 수 있습니다. 확장 가능한 API 구축, 시스템 성능 최적화, 또는 전체 스택 솔루션에 기여하는 등 다양한 분야에 능숙하게 참여할 수 있습니다. 저는 각 프로젝트에 맞는 최적의 도구를 찾는 것과 새로운 도전을 즐깁니다.</p><p>[[당신과 협업]]하기를 기대하고 있습니다!</p>"
                        }
                    }
                }
            ]
        },

        {
            "id": 3,
            "component": "ArticleTestimonials",
            "locales": {
                "en": {"title": "Client {{testimonials}}"},
                "es": {"title": "Testimonios de {{clientes}}"},
                "fr": {"title": "Témoignages de {{clients}}"},
                "ko": {"title": "{{고객}} 추천사"}
            },
            "settings": {
                "order_items_by": "id",
                "order_items_sort": "asc"
            },
            "items": [
                {
                    "id": 1,
                    "label": "Anita Bath",
                    "link": {"href": "https://linkedin.com", "tooltipString": "open_website"},
                    "img": "images/pictures/testimonial-person-female-1.png",
                    "faIcon": "",
                    "faIconColors": {"bg": "", "fill": ""},
                    "locales": {
                        "en": {
                            "title": "CEO at [[SalesForce]]",
                            "text": "Working with Leo was a truly [[transformative experience]]. His outstanding programming skills and collaborative spirit not only elevated the quality of our project but also brought a renewed sense of motivation and purpose to us."
                        },
                        "es": {
                            "title": "CEO en [[SalesForce]]",
                            "text": "Trabajar con Leo fue una [[experiencia transformadora]]. Su gran habilidad para programar y su espíritu colaborativo mejoraron el proyecto y nos devolvieron la motivación y el propósito."
                        },
                        "fr": {
                            "title": "PDG de [[SalesForce]]",
                            "text": "Travailler avec Leo fut une [[expérience transformante]]. Ses compétences en programmation et son esprit d’équipe ont élevé le projet et ravivé notre motivation et notre but."
                        },
                        "ko": {
                            "title": "세일즈포스 CEO",
                            "text": "Leo와 함께한 시간은 [[변화의 경험]]이었습니다. 그의 뛰어난 프로그래밍 실력과 협업 정신은 프로젝트 품질을 높이고 우리에게 새로운 동기를 불어넣었습니다."
                        }
                    }
                },
                {
                    "id": 2,
                    "label": "Lou Natic",
                    "link": {"href": "https://github.com", "tooltipString": "open_website"},
                    "img": "images/pictures/testimonial-person-male-1.png",
                    "faIcon": "",
                    "faIconColors": {"bg": "", "fill": ""},
                    "locales": {
                        "en": {
                            "title": "Lead Developer at [[GitHub]]",
                            "text": "Having Leo on our team was an invaluable asset. His [[deep programming insights and mentorship]] not only elevated our projects but also empowered us to tackle every challenge with confidence and creativity."
                        },
                        "es": {
                            "title": "Desarrollador Principal en [[GitHub]]",
                            "text": "Tener a Leo fue un recurso invaluable. Sus [[profundos conocimientos y mentoría]] mejoraron nuestros proyectos y nos dieron confianza para afrontar cualquier desafío con creatividad."
                        },
                        "fr": {
                            "title": "Développeur Principal chez [[GitHub]]",
                            "text": "La présence de Leo fut un atout inestimable. Ses [[connaissances en programmation et son mentorat]] ont renforcé nos projets et notre capacité à relever les défis avec assurance."
                        },
                        "ko": {
                            "title": "[[GitHub]] 수석 개발자",
                            "text": "Leo는 소중한 자산이었습니다. 그의 [[깊은 프로그래밍 통찰력과 멘토링]]은 프로젝트를 향상시키고 도전을 자신감과 창의성으로 해결할 수 있게 해주었습니다."
                        }
                    }
                },
                {
                    "id": 3,
                    "label": "Paige Turner",
                    "link": {"href": "", "tooltipString": ""},
                    "img": "images/pictures/testimonial-person-female-2.png",
                    "faIcon": "",
                    "faIconColors": {"bg": "", "fill": ""},
                    "locales": {
                        "en": {
                            "title": "Managing Director at [[Dingga]]",
                            "text": "Collaborating with Leo was a true [[game changer]] for our entire development process. His [[deep technical expertise]], creative problem-solving, and proactive mindset were absolutely invaluable."
                        },
                        "es": {
                            "title": "Directora General en [[Dingga]]",
                            "text": "Colaborar con Leo fue un verdadero [[punto de inflexión]]. Su [[gran experiencia técnica]], creatividad y mentalidad proactiva fueron absolutamente invaluables para nuestro equipo."
                        },
                        "fr": {
                            "title": "Directrice Générale chez [[Dingga]]",
                            "text": "Travailler avec Leo a été un vrai [[tournant]]. Son [[expertise technique approfondie]], sa créativité et sa proactivité ont été d’une valeur inestimable pour notre développement."
                        },
                        "ko": {
                            "title": "딩가 전무이사",
                            "text": "Leo와의 협업은 진정한 [[게임 체인저]]였습니다. 그의 [[깊이 있는 기술 전문성]], 창의적인 문제 해결력, 능동적인 태도는 매우 소중한 자산이었습니다."
                        }
                    }
                },
                {
                    "id": 4,
                    "label": "Chris P. Bacon",
                    "link": {"href": "https://dribbble.com", "tooltipString": "open_website"},
                    "img": "images/pictures/testimonial-person-male-2.png",
                    "faIcon": "",
                    "faIconColors": {"bg": "", "fill": ""},
                    "locales": {
                        "en": {
                            "title": "Creative Director at [[Dribbble]]",
                            "text": "Leo Hsu's [[attention to detail]] and his [[innovative thinking]] brought a fresh perspective to our whole design process! Simply amazing!"
                        },
                        "es": {
                            "title": "Director Creativo en [[Dribbble]]",
                            "text": "La [[atención al detalle]] y el [[pensamiento innovador]] de Leo Hsu aportaron una perspectiva fresca a todo nuestro proceso de diseño. ¡Simplemente increíble!"
                        },
                        "fr": {
                            "title": "Directeur Créatif chez [[Dribbble]]",
                            "text": "L’[[attention aux détails]] et la [[pensée innovante]] de Leo Hsu ont apporté une perspective nouvelle à tout notre processus de design ! Simplement incroyable !"
                        },
                        "ko": {
                            "title": "[[Dribbble]] 크리에이티브 디렉터",
                            "text": "마크 최의 [[세심한 배려]]와 [[혁신적인 사고]]가 전체 디자인 과정에 신선한 시각을 가져왔습니다! 정말 놀랍습니다!"
                        }
                    }
                }
            ]
        },

        {
            "id": 4,
            "component": "ArticleInfoList",
            "settings": {
                "order_items_by": "id",
                "order_items_sort": "asc"
            },
            "locales": {
                "en": {"title": "Personal {{interests}}"},
                "es": {"title": "Intereses {{personales}}"},
                "fr": {"title": "Intérêts {{personnels}} "},
                "ko": {"title": "개인 {{관심사}}"}
            },
            "items": [
                {
                    "id": 1,
                    "faIcon": "fa-solid fa-video",
                    "faIconColors": {"bg": "", "fill": ""},
                    "label": null,
                    "link": {"href": null, "tooltipString": null},
                    "copyToClipboardButton": false,
                    "locales": {
                        "en": {
                            "title": "{{AI}} video editing",
                            "text": "Learning to use AI tools to enhance my videos."
                        },
                        "es": {
                            "title": "Edición de video con {{AI}}",
                            "text": "Aprendiendo a usar herramientas de IA para mejorar mis videos."
                        },
                        "fr": {
                            "title": "Édition vidéo avec {{IA}}",
                            "text": "Apprendre à utiliser des outils d'IA pour améliorer mes vidéos."
                        },
                        "ko": {
                            "title": "{{AI}} 비디오 편집",
                            "text": "AI 도구를 사용하여 내 영상을 향상시키는 방법 배우기."
                        }
                    }
                },
                {
                    "id": 2,
                    "faIcon": "fa-solid fa-palette",
                    "faIconColors": {"bg": "", "fill": ""},
                    "label": null,
                    "link": {"href": null, "tooltipString": null},
                    "copyToClipboardButton": false,
                    "locales": {
                        "en": {
                            "title": "{{Arts}} & Illustration",
                            "text": "Practicing digital art and exploring new styles."
                        },
                        "es": {
                            "title": "{{Arte}} y Ilustración",
                            "text": "Practicando arte digital y explorando nuevos estilos."
                        },
                        "fr": {
                            "title": "{{Arts}} & Illustration",
                            "text": "Pratiquer l'art numérique et explorer de nouveaux styles."
                        },
                        "ko": {
                            "title": "{{예술}} 및 일러스트레이션",
                            "text": "디지털 아트를 연습하고 새로운 스타일을 탐험하기."
                        }
                    }
                },
                {
                    "id": 3,
                    "faIcon": "fa-solid fa-chart-line",
                    "faIconColors": {"bg": "", "fill": ""},
                    "label": null,
                    "link": {"href": null, "tooltipString": null},
                    "copyToClipboardButton": false,
                    "locales": {
                        "en": {
                            "title": "{{Investing}} & Finance",
                            "text": "Learning the basics of stocks and personal finance."
                        },
                        "es": {
                            "title": "{{Inversión}} y Finanzas",
                            "text": "Aprendiendo los conceptos básicos de acciones y finanzas personales."
                        },
                        "fr": {
                            "title": "{{Investissement}} & Finance",
                            "text": "Apprendre les bases des actions et des finances personnelles."
                        },
                        "ko": {
                            "title": "{{투자}} 및 재정 관리",
                            "text": "주식과 개인 재정의 기초 배우기."
                        }
                    }
                },
                {
                    "id": 4,
                    "faIcon": "fa-solid fa-window-restore",
                    "faIconColors": {"bg": "", "fill": ""},
                    "label": null,
                    "link": {"href": null, "tooltipString": null},
                    "copyToClipboardButton": false,
                    "locales": {
                        "en": {
                            "title": "{{UX}} design",
                            "text": "Studying user experience principles."
                        },
                        "es": {
                            "title": "Diseño {{UX}}",
                            "text": "Estudiando los principios de la experiencia del usuario."
                        },
                        "fr": {
                            "title": "Conception {{UX}}",
                            "text": "Étudier les principes de l'expérience utilisateur."
                        },
                        "ko": {
                            "title": "{{UX}} 디자인",
                            "text": "사용자 경험 원칙을 공부하기."
                        }
                    }
                },
                {
                    "id": 5,
                    "img": "",
                    "faIcon": "fa-solid fa-camera-retro",
                    "faIconColors": {"bg": "", "fill": ""},
                    "label": null,
                    "link": {"href": null, "tooltipString": null},
                    "copyToClipboardButton": false,
                    "locales": {
                        "en": {
                            "title": "{{Photography}} & Photoshop",
                            "text": "Enhancing photos through creative editing techniques."
                        },
                        "es": {
                            "title": "{{Fotografía}} y Photoshop",
                            "text": "Mejorando fotos a través de técnicas creativas de edición."
                        },
                        "fr": {
                            "title": "{{Photographie}} & Photoshop",
                            "text": "Améliorer des photos avec des techniques de montage créatives."
                        },
                        "ko": {
                            "title": "{{사진}} 및 포토샵",
                            "text": "창의적인 편집 기술을 통해 사진을 향상시키기."
                        }
                    }
                },
                {
                    "id": 6,
                    "faIcon": "fa-solid fa-drum-steelpan",
                    "faIconColors": {"bg": "", "fill": ""},
                    "label": null,
                    "link": {"href": null, "tooltipString": null},
                    "copyToClipboardButton": false,
                    "locales": {
                        "en": {
                            "title": "Playing {{drums}}",
                            "text": "Exploring different genres and improving my skills."
                        },
                        "es": {
                            "title": "Tocar {{batería}}",
                            "text": "Explorando diferentes géneros y mejorando mis habilidades."
                        },
                        "fr": {
                            "title": "Jouer de la {{batterie}}",
                            "text": "Explorer différents genres et améliorer mes compétences."
                        },
                        "ko": {
                            "title": "{{드럼}} 연주",
                            "text": "다양한 장르를 탐험하고 기술을 향상시키기."
                        }
                    }
                }
            ]
        }
    ]
}